pcapng/__init__.py
pcapng/_compat.py
pcapng/blocks.py
pcapng/exceptions.py
pcapng/flags.py
pcapng/scanner.py
pcapng/strictness.py
pcapng/structs.py
pcapng/utils.py
pcapng/writer.py
pcapng/constants/__init__.py
pcapng/constants/block_types.py
pcapng/constants/link_types.py
python_pcapng-2.1.1.dist-info/LICENSE
python_pcapng-2.1.1.dist-info/METADATA
python_pcapng-2.1.1.dist-info/WHEEL
python_pcapng-2.1.1.dist-info/top_level.txt
python_pcapng-2.1.1.dist-info/RECORD
