Metadata-Version: 2.1
Name: python-pcapng
Version: 2.1.1
Summary: Library to read/write the pcap-ng format used by various packet sniffers.
Home-page: https://github.com/rshk/python-pcapng
Author: Samuele Santi
Author-email: samuele@samuelesanti.com
License: Apache-2.0
Classifier: Development Status :: 5 - Production/Stable
Classifier: License :: OSI Approved :: Apache Software License
Classifier: Programming Language :: Python :: 3.5
Classifier: Programming Language :: Python :: 3.6
Classifier: Programming Language :: Python :: 3.7
Classifier: Programming Language :: Python :: 3.8
Classifier: Programming Language :: Python :: Implementation :: CPython
Requires-Python: ~=3.5
Provides-Extra: dev
License-File: LICENSE
